eyeliner/__init__.py
eyeliner/detectors.py
eyeliner/eyeliner.py
eyeliner/lightglue/__init__.py
eyeliner/lightglue/aliked.py
eyeliner/lightglue/disk.py
eyeliner/lightglue/lightglue.py
eyeliner/lightglue/sift.py
eyeliner/lightglue/superpoint.py
eyeliner/lightglue/utils.py
eyeliner/lightglue/viz2d.py
eyeliner/utils.py
eyeliner/weights/superpoint_lightglue.pth
eyeliner/weights/superpoint_v1.pth
eyeliner-0.1.1.dist-info/METADATA
eyeliner-0.1.1.dist-info/WHEEL
eyeliner-0.1.1.dist-info/entry_points.txt
eyeliner-0.1.1.dist-info/RECORD
