Metadata-Version: 2.3
Name: eyeliner
Version: 0.1.1
Summary: Automatic Image Registration using Retinal Landmarks
License: MIT
Author: Aveturi13
Author-email: advaithveturi@gmail.com
Requires-Python: >=3.10,<4.0
Classifier: License :: OSI Approved :: MIT License
Classifier: Programming Language :: Python :: 3
Classifier: Programming Language :: Python :: 3.10
Classifier: Programming Language :: Python :: 3.11
Classifier: Programming Language :: Python :: 3.12
Classifier: Programming Language :: Python :: 3.13
Requires-Dist: albumentations (>=1.4.21,<2.0.0)
Requires-Dist: coloredlogs (>=15.0.1,<16.0.0)
Requires-Dist: jupyter (>=1.0.0,<2.0.0)
Requires-Dist: kornia (>=0.7.2,<0.8.0)
Requires-Dist: matplotlib (>=3.8.4,<4.0.0)
Requires-Dist: monai (>=1.3.0,<2.0.0)
Requires-Dist: numpy (>=1.26.4,<2.0.0)
Requires-Dist: opencv-python (>=4.9.0.80,<5.0.0.0)
Requires-Dist: pandas (>=2.2.2,<3.0.0)
Requires-Dist: patchify (>=0.2.3,<0.3.0)
Requires-Dist: scikit-image (>=0.23.2,<0.24.0)
Requires-Dist: scipy (>=1.13.0,<2.0.0)
Requires-Dist: termcolor (>=2.5.0,<3.0.0)
Requires-Dist: torch (>=2.2.2,<3.0.0)
Requires-Dist: torchvision (>=0.17.2,<0.18.0)
Requires-Dist: tqdm (>=4.66.2,<5.0.0)
Project-URL: Homepage, https://github.com/QTIM-Lab/EyeLiner
Project-URL: Repository, https://github.com/QTIM-Lab/EyeLiner
